dt_sms_sdk/__init__.py
dt_sms_sdk/account.py
dt_sms_sdk/dashboard.py
dt_sms_sdk/iso2_mapper.py
dt_sms_sdk/message.py
dt_sms_sdk/phone_number.py
dt_sms_sdk/pricing.py
dt_sms_sdk/sms_api.py
unofficial_dt_sms_api_sdk-1.0.3.dist-info/LICENSE
unofficial_dt_sms_api_sdk-1.0.3.dist-info/METADATA
unofficial_dt_sms_api_sdk-1.0.3.dist-info/WHEEL
unofficial_dt_sms_api_sdk-1.0.3.dist-info/top_level.txt
unofficial_dt_sms_api_sdk-1.0.3.dist-info/RECORD
