Metadata-Version: 2.1
Name: unofficial-dt-sms-api-sdk
Version: 1.0.3
Summary: Unofficial Python-SDK for the SMS API of Deutsche Telekom
Home-page: https://github.com/Anrufliste/dt-sms-api-sdk-python
Author: Emil Thies
Author-email: uDTSMSAPISDK@anrufliste.com
Requires-Python: >=3.7
License-File: LICENSE
Requires-Dist: requests (==2.28.2)
Requires-Dist: requests-mock
